woke/__init__.py
woke/analysis/__init__.py
woke/analysis/cfg.py
woke/analysis/detectors/__init__.py
woke/analysis/detectors/api.py
woke/analysis/detectors/balance_state_var.py
woke/analysis/detectors/call_options_not_called.py
woke/analysis/detectors/ownable.py
woke/analysis/detectors/reentrancy.py
woke/analysis/detectors/unchecked_return_value.py
woke/analysis/detectors/unsafe_delegatecall.py
woke/analysis/detectors/unsafe_selfdestruct.py
woke/analysis/detectors/utils.py
woke/ast/__init__.py
woke/ast/enums.py
woke/ast/nodes.py
woke/ast/types.py
woke/ast/ir/__init__.py
woke/ast/ir/abc.py
woke/ast/ir/reference_resolver.py
woke/ast/ir/declaration/__init__.py
woke/ast/ir/declaration/abc.py
woke/ast/ir/declaration/contract_definition.py
woke/ast/ir/declaration/enum_definition.py
woke/ast/ir/declaration/enum_value.py
woke/ast/ir/declaration/error_definition.py
woke/ast/ir/declaration/event_definition.py
woke/ast/ir/declaration/function_definition.py
woke/ast/ir/declaration/modifier_definition.py
woke/ast/ir/declaration/struct_definition.py
woke/ast/ir/declaration/user_defined_value_type_definition.py
woke/ast/ir/declaration/variable_declaration.py
woke/ast/ir/expression/__init__.py
woke/ast/ir/expression/abc.py
woke/ast/ir/expression/assignment.py
woke/ast/ir/expression/binary_operation.py
woke/ast/ir/expression/conditional.py
woke/ast/ir/expression/elementary_type_name_expression.py
woke/ast/ir/expression/function_call.py
woke/ast/ir/expression/function_call_options.py
woke/ast/ir/expression/identifier.py
woke/ast/ir/expression/index_access.py
woke/ast/ir/expression/index_range_access.py
woke/ast/ir/expression/literal.py
woke/ast/ir/expression/member_access.py
woke/ast/ir/expression/new_expression.py
woke/ast/ir/expression/tuple_expression.py
woke/ast/ir/expression/unary_operation.py
woke/ast/ir/meta/__init__.py
woke/ast/ir/meta/identifier_path.py
woke/ast/ir/meta/import_directive.py
woke/ast/ir/meta/inheritance_specifier.py
woke/ast/ir/meta/modifier_invocation.py
abch_woke-1.0.0.dist-info/LICENSE
abch_woke-1.0.0.dist-info/METADATA
abch_woke-1.0.0.dist-info/WHEEL
abch_woke-1.0.0.dist-info/entry_points.txt
abch_woke-1.0.0.dist-info/top_level.txt
abch_woke-1.0.0.dist-info/RECORD
