Metadata-Version: 2.1
Name: abch-woke
Version: 1.0.0
Summary: Woke is a Python-based development and testing framework for Solidity.
Home-page: https://github.com/Ackee-Blockchain/woke
Author: Ackee Blockchain
Author-email: hello@ackeeblockchain.com
License: ISC
Keywords: solidity,ethereum,blockchain,review,audit,security,compiler,solidity audit,solidity security
Requires-Python: >=3.7
License-File: LICENSE
Requires-Dist: pydantic (>=1.9.1)
Requires-Dist: typing-extensions (<5,>=4.0)
Requires-Dist: aiohttp (<4,>=3.8)
Requires-Dist: aiofiles (>=0.8.0)
Requires-Dist: tomli (<3,>=2.0.0)
Requires-Dist: networkx (<3,>=2.5)
Requires-Dist: pycryptodomex (<4,>=3.12)
Requires-Dist: click (<9,>=8)
Requires-Dist: rich (>=10.16)
Requires-Dist: pathvalidate (<3,>=2.5.0)
Requires-Dist: intervaltree (>=3.1)
Provides-Extra: dev
Requires-Dist: black ; extra == 'dev'
Requires-Dist: ipython (<8) ; extra == 'dev'
Requires-Dist: mkdocs-material (>=8.3.9) ; extra == 'dev'
Requires-Dist: mkdocstrings[python] ; extra == 'dev'
Requires-Dist: pymdown-extensions (>=9.0) ; extra == 'dev'
Requires-Dist: pygments ; extra == 'dev'
Requires-Dist: mike ; extra == 'dev'
Requires-Dist: isort (<6,>=5.10.0) ; extra == 'dev'
Provides-Extra: fuzzer
Requires-Dist: eth-brownie (>=1.16) ; extra == 'fuzzer'
Requires-Dist: tblib (<2,>=1.7.0) ; extra == 'fuzzer'
Requires-Dist: ipdb ; extra == 'fuzzer'
Provides-Extra: tests
Requires-Dist: pytest (<7.0,>=6.2.5) ; extra == 'tests'
Requires-Dist: pytest-asyncio (<1,>=0.17) ; extra == 'tests'
Requires-Dist: GitPython (<4,>=3.1.20) ; extra == 'tests'
